LICENSE
MANIFEST.in
README
setup.py
doc/Makefile
doc/conf.py
doc/index.rst
sqlamp/__init__.py
sqlamp.egg-info/PKG-INFO
sqlamp.egg-info/SOURCES.txt
sqlamp.egg-info/dependency_links.txt
sqlamp.egg-info/requires.txt
sqlamp.egg-info/top_level.txt
tests/__init__.py
tests/_testlib.py
tests/benchmark-tests.py
tests/doctests.py
tests/functional-tests.py
tests/run-all.py