Metadata-Version: 1.0
Name: sqlamp
Version: 0.3
Summary: sqlamp is an implementation of Materialized Path for SQLAlchemy.
Home-page: http://sqlamp.angri.ru
Author: Anton Gritsay
Author-email: anton@angri.ru
License: BSD
Download-URL: http://sqlamp.angri.ru/sqlamp-0.3.tar.gz
Platform: any
Classifier: Development Status :: 3 - Alpha
Classifier: Environment :: Plugins
Classifier: Intended Audience :: Developers
Classifier: License :: OSI Approved :: BSD License
Classifier: Operating System :: OS Independent
Classifier: Programming Language :: Python
Classifier: Topic :: Database
